langchain_gradient/__init__.py
langchain_gradient/chat_models.py
langchain_gradient/constants.py
langchain_gradient-0.1.24.dist-info/METADATA
langchain_gradient-0.1.24.dist-info/WHEEL
langchain_gradient-0.1.24.dist-info/licenses/LICENSE
langchain_gradient-0.1.24.dist-info/RECORD
