Metadata-Version: 2.4
Name: langchain-gradient
Version: 0.1.24
Summary: An integration package connecting Digitalocean and LangChain
License: MIT
License-File: LICENSE
Requires-Python: >=3.9,<4.0
Classifier: License :: OSI Approved :: MIT License
Classifier: Programming Language :: Python :: 3
Classifier: Programming Language :: Python :: 3.9
Classifier: Programming Language :: Python :: 3.10
Classifier: Programming Language :: Python :: 3.11
Classifier: Programming Language :: Python :: 3.12
Classifier: Programming Language :: Python :: 3.13
Classifier: Programming Language :: Python :: 3.14
Requires-Dist: c63a5cfe-b235-4fbe-8bbb-82a9e02a482a-python (>=0.1.0a17,<0.2.0)
Requires-Dist: gradient (>=3.0.0,<4.0.0)
Requires-Dist: langchain-core (>=0.3.81,<0.4.0)
Requires-Dist: langchain-tests (>=0.3.20,<0.4.0)
Requires-Dist: python-digitalocean (>=1.17.0,<2.0.0)
Requires-Dist: python-dotenv (>=1.0.0,<2.0.0)
Requires-Dist: typing_extensions (>=4.0.0,<5.0.0)
Project-URL: Repository, https://github.com/langchain-ai/langchain
Project-URL: Release Notes, https://github.com/langchain-ai/langchain/releases?q=tag%3A%22gradient%3D%3D0%22&expanded=true
Project-URL: Source Code, https://github.com/langchain-ai/langchain/tree/master/libs/partners/gradient
